cdo_api_py/Client.py
cdo_api_py/__init__.py
cdo_api_py/conf.py
cdo_api_py/exceptions.py
cdo_api_py-1.0.0.dev13.dist-info/DESCRIPTION.rst
cdo_api_py-1.0.0.dev13.dist-info/METADATA
cdo_api_py-1.0.0.dev13.dist-info/RECORD
cdo_api_py-1.0.0.dev13.dist-info/WHEEL
cdo_api_py-1.0.0.dev13.dist-info/metadata.json
cdo_api_py-1.0.0.dev13.dist-info/top_level.txt
