Metadata-Version: 2.0
Name: cdo-api-py
Version: 1.0.0.dev13
Summary: Python interface to the climate data online api
Home-page: https://github.com/Jwely/cdo-api-py
Author: Jwely
Author-email: jeff.ely.08@gmail.com
License: MIT
Keywords: weather data,noaa,ncdc,climate data online,cdo
Platform: UNKNOWN
Classifier: Development Status :: 4 - Beta
Classifier: Intended Audience :: Developers
Classifier: Topic :: Software Development
Classifier: License :: OSI Approved :: MIT License
Classifier: Programming Language :: Python :: 3 :: Only
Classifier: Programming Language :: Python :: 3
Classifier: Programming Language :: Python :: 3.3
Classifier: Programming Language :: Python :: 3.4
Classifier: Programming Language :: Python :: 3.5
Classifier: Programming Language :: Python :: 3.6
Provides-Extra: dev
Provides-Extra: test
Requires-Dist: requests
Requires-Dist: pandas
Provides-Extra: dev
Provides-Extra: test
